{
  "pAccountStandardCurrentFee": {
    "precision": 1.0,
    "recall": 1.0,
    "f1-score": 1.0,
    "support": 15
  },
  "pAccountBudgetMinimumBalance": {
    "precision": 1.0,
    "recall": 1.0,
    "f1-score": 1.0,
    "support": 13
  },
  "pAccountBudgetInterestRate": {
    "precision": 1.0,
    "recall": 1.0,
    "f1-score": 1.0,
    "support": 15
  },
  "pAccountSavingsDocument": {
    "precision": 1.0,
    "recall": 1.0,
    "f1-score": 1.0,
    "support": 14
  },
  "pAccountIgnitionWhoApply": {
    "precision": 1.0,
    "recall": 1.0,
    "f1-score": 1.0,
    "support": 12
  },
  "pAccountPrestigeCurrentInterestRate": {
    "precision": 1.0,
    "recall": 1.0,
    "f1-score": 1.0,
    "support": 15
  },
  "pAccountPremierCurrent": {
    "precision": 1.0,
    "recall": 1.0,
    "f1-score": 1.0,
    "support": 15
  },
  "pAccountCurrentInquiry": {
    "precision": 1.0,
    "recall": 1.0,
    "f1-score": 1.0,
    "support": 15
  },
  "pAccountPrestigeCurrentFee": {
    "precision": 1.0,
    "recall": 1.0,
    "f1-score": 1.0,
    "support": 15
  },
  "pAccountIgnitionDocument": {
    "precision": 1.0,
    "recall": 1.0,
    "f1-score": 1.0,
    "support": 14
  },
  "pAccountInquiry": {
    "precision": 0.9444444444444444,
    "recall": 1.0,
    "f1-score": 0.9714285714285714,
    "support": 17
  },
  "pAccountIgnition": {
    "precision": 1.0,
    "recall": 1.0,
    "f1-score": 1.0,
    "support": 15
  },
  "pAccountFixedDepositBenefit": {
    "precision": 1.0,
    "recall": 1.0,
    "f1-score": 1.0,
    "support": 14
  },
  "pAccountSavingsHowApply": {
    "precision": 1.0,
    "recall": 1.0,
    "f1-score": 1.0,
    "support": 15
  },
  "pAccountStandardCurrentMinimumBalance": {
    "precision": 1.0,
    "recall": 1.0,
    "f1-score": 1.0,
    "support": 13
  },
  "pAccountStandardCurrentInterestRate": {
    "precision": 1.0,
    "recall": 1.0,
    "f1-score": 1.0,
    "support": 15
  },
  "pAccountBudgetMinimumInitialDeposit": {
    "precision": 1.0,
    "recall": 1.0,
    "f1-score": 1.0,
    "support": 13
  },
  "pAccountPrestigeCurrentFreeDebitCard": {
    "precision": 1.0,
    "recall": 1.0,
    "f1-score": 1.0,
    "support": 13
  },
  "pAccountPremierCurrentODFacility": {
    "precision": 1.0,
    "recall": 1.0,
    "f1-score": 1.0,
    "support": 13
  },
  "pAccountStandardCurrentFreeDebitCard": {
    "precision": 1.0,
    "recall": 1.0,
    "f1-score": 1.0,
    "support": 13
  },
  "pAccountSavingsFee": {
    "precision": 1.0,
    "recall": 1.0,
    "f1-score": 1.0,
    "support": 15
  },
  "pAccountSavingsMinimumBalance": {
    "precision": 1.0,
    "recall": 1.0,
    "f1-score": 1.0,
    "support": 13
  },
  "pAccountSavingsWhoApply": {
    "precision": 1.0,
    "recall": 1.0,
    "f1-score": 1.0,
    "support": 12
  },
  "pAccountPrestigeCurrentDocument": {
    "precision": 1.0,
    "recall": 1.0,
    "f1-score": 1.0,
    "support": 14
  },
  "pAccountStandardCurrentHowApply": {
    "precision": 1.0,
    "recall": 1.0,
    "f1-score": 1.0,
    "support": 14
  },
  "pAccountStandardCurrentWhoApply": {
    "precision": 1.0,
    "recall": 1.0,
    "f1-score": 1.0,
    "support": 12
  },
  "pAccountIgnitionODFacility": {
    "precision": 1.0,
    "recall": 1.0,
    "f1-score": 1.0,
    "support": 13
  },
  "pAccountFixedDepositMinimumInitialDeposit": {
    "precision": 1.0,
    "recall": 1.0,
    "f1-score": 1.0,
    "support": 13
  },
  "pAccountBudgetDocument": {
    "precision": 1.0,
    "recall": 1.0,
    "f1-score": 1.0,
    "support": 14
  },
  "pAccountPrestigeCurrentInterestPayoutFrequency": {
    "precision": 1.0,
    "recall": 1.0,
    "f1-score": 1.0,
    "support": 13
  },
  "pAccountFixedDepositHowApply": {
    "precision": 1.0,
    "recall": 1.0,
    "f1-score": 1.0,
    "support": 14
  },
  "pAccountBudgetODFacility": {
    "precision": 1.0,
    "recall": 1.0,
    "f1-score": 1.0,
    "support": 13
  },
  "pAccountBudgetCurrency": {
    "precision": 1.0,
    "recall": 1.0,
    "f1-score": 1.0,
    "support": 15
  },
  "pAccountBudgetBenefit": {
    "precision": 1.0,
    "recall": 1.0,
    "f1-score": 1.0,
    "support": 14
  },
  "pAccountIgnitionInterestRate": {
    "precision": 1.0,
    "recall": 1.0,
    "f1-score": 1.0,
    "support": 15
  },
  "pAccountFixedDepositCurrency": {
    "precision": 1.0,
    "recall": 1.0,
    "f1-score": 1.0,
    "support": 15
  },
  "pAccountIgnitionFee": {
    "precision": 1.0,
    "recall": 1.0,
    "f1-score": 1.0,
    "support": 15
  },
  "pAccountSavingsInterestPayoutFrequency": {
    "precision": 1.0,
    "recall": 1.0,
    "f1-score": 1.0,
    "support": 13
  },
  "pAccountPrestigeCurrentMinimumBalance": {
    "precision": 1.0,
    "recall": 1.0,
    "f1-score": 1.0,
    "support": 13
  },
  "pAccountIgnitionInterestPayoutFrequency": {
    "precision": 1.0,
    "recall": 1.0,
    "f1-score": 1.0,
    "support": 13
  },
  "pAccountSavingsFreeDebitCard": {
    "precision": 1.0,
    "recall": 1.0,
    "f1-score": 1.0,
    "support": 13
  },
  "pAccountFixedDepositInterestRate": {
    "precision": 1.0,
    "recall": 1.0,
    "f1-score": 1.0,
    "support": 15
  },
  "pAccountPremierCurrentHowApply": {
    "precision": 1.0,
    "recall": 1.0,
    "f1-score": 1.0,
    "support": 14
  },
  "pAccountPremierCurrentCurrency": {
    "precision": 1.0,
    "recall": 1.0,
    "f1-score": 1.0,
    "support": 15
  },
  "pAccountPremierCurrentInterestPayoutFrequency": {
    "precision": 1.0,
    "recall": 1.0,
    "f1-score": 1.0,
    "support": 13
  },
  "pAccountSavingsODFacility": {
    "precision": 1.0,
    "recall": 1.0,
    "f1-score": 1.0,
    "support": 13
  },
  "pAccountSavingsMinimumInitialDeposit": {
    "precision": 1.0,
    "recall": 1.0,
    "f1-score": 1.0,
    "support": 13
  },
  "pAccountBudgetFreeDebitCard": {
    "precision": 1.0,
    "recall": 1.0,
    "f1-score": 1.0,
    "support": 13
  },
  "pAccountStandardCurrentODFacility": {
    "precision": 1.0,
    "recall": 1.0,
    "f1-score": 1.0,
    "support": 13
  },
  "pAccountSavingsBenefit": {
    "precision": 1.0,
    "recall": 1.0,
    "f1-score": 1.0,
    "support": 14
  },
  "pAccountPremierCurrentWhoApply": {
    "precision": 1.0,
    "recall": 1.0,
    "f1-score": 1.0,
    "support": 12
  },
  "pAccountPremierCurrentFee": {
    "precision": 1.0,
    "recall": 1.0,
    "f1-score": 1.0,
    "support": 15
  },
  "pAccountStandardCurrentCurrency": {
    "precision": 1.0,
    "recall": 1.0,
    "f1-score": 1.0,
    "support": 15
  },
  "pAccountPremierCurrentInterestRate": {
    "precision": 1.0,
    "recall": 1.0,
    "f1-score": 1.0,
    "support": 15
  },
  "pAccountStandardCurrentInterestPayoutFrequency": {
    "precision": 1.0,
    "recall": 1.0,
    "f1-score": 1.0,
    "support": 13
  },
  "pAccountPremierCurrentMinimumInitialDeposit": {
    "precision": 1.0,
    "recall": 1.0,
    "f1-score": 1.0,
    "support": 13
  },
  "pAccountPrestigeCurrentWhoApply": {
    "precision": 1.0,
    "recall": 1.0,
    "f1-score": 1.0,
    "support": 12
  },
  "pAccountBudgetFee": {
    "precision": 1.0,
    "recall": 1.0,
    "f1-score": 1.0,
    "support": 15
  },
  "pAccountStandardCurrentBenefit": {
    "precision": 1.0,
    "recall": 1.0,
    "f1-score": 1.0,
    "support": 14
  },
  "pAccountFixedDepositDocument": {
    "precision": 1.0,
    "recall": 1.0,
    "f1-score": 1.0,
    "support": 15
  },
  "pAccountBudgetWhoApply": {
    "precision": 1.0,
    "recall": 1.0,
    "f1-score": 1.0,
    "support": 12
  },
  "pAccountBudgetHowApply": {
    "precision": 1.0,
    "recall": 1.0,
    "f1-score": 1.0,
    "support": 14
  },
  "pAccountFixedDepositODFacility": {
    "precision": 1.0,
    "recall": 1.0,
    "f1-score": 1.0,
    "support": 13
  },
  "pAccountIgnitionBenefit": {
    "precision": 1.0,
    "recall": 1.0,
    "f1-score": 1.0,
    "support": 14
  },
  "pAccountFixedDepositWhoApply": {
    "precision": 1.0,
    "recall": 1.0,
    "f1-score": 1.0,
    "support": 12
  },
  "pAccountPremierCurrentFreeDebitCard": {
    "precision": 1.0,
    "recall": 1.0,
    "f1-score": 1.0,
    "support": 13
  },
  "pAccountFixedDepositPrematureClosure": {
    "precision": 1.0,
    "recall": 1.0,
    "f1-score": 1.0,
    "support": 13
  },
  "pAccountPrestigeCurrentBenefit": {
    "precision": 1.0,
    "recall": 1.0,
    "f1-score": 1.0,
    "support": 14
  },
  "pAccountFixedDeposit": {
    "precision": 1.0,
    "recall": 0.9444444444444444,
    "f1-score": 0.9714285714285714,
    "support": 18
  },
  "pAccountIgnitionCurrency": {
    "precision": 1.0,
    "recall": 1.0,
    "f1-score": 1.0,
    "support": 15
  },
  "pAccountIgnitionHowApply": {
    "precision": 1.0,
    "recall": 1.0,
    "f1-score": 1.0,
    "support": 14
  },
  "pAccountStandardCurrentDocument": {
    "precision": 1.0,
    "recall": 1.0,
    "f1-score": 1.0,
    "support": 14
  },
  "pAccountPremierCurrentBenefit": {
    "precision": 1.0,
    "recall": 1.0,
    "f1-score": 1.0,
    "support": 14
  },
  "pAccountFixedDepositFee": {
    "precision": 1.0,
    "recall": 1.0,
    "f1-score": 1.0,
    "support": 15
  },
  "pAccountPremierCurrentDocument": {
    "precision": 1.0,
    "recall": 1.0,
    "f1-score": 1.0,
    "support": 14
  },
  "pAccountStandardCurrentMinimumInitialDeposit": {
    "precision": 1.0,
    "recall": 1.0,
    "f1-score": 1.0,
    "support": 13
  },
  "pAccountBudgetInterestPayoutFrequency": {
    "precision": 1.0,
    "recall": 1.0,
    "f1-score": 1.0,
    "support": 13
  },
  "pAccountIgnitionMinimumBalance": {
    "precision": 1.0,
    "recall": 1.0,
    "f1-score": 1.0,
    "support": 13
  },
  "pAccountPremierCurrentMinimumBalance": {
    "precision": 1.0,
    "recall": 1.0,
    "f1-score": 1.0,
    "support": 13
  },
  "pAccountStandardCurrent": {
    "precision": 1.0,
    "recall": 1.0,
    "f1-score": 1.0,
    "support": 15
  },
  "pAccountIgnitionMinimumInitialDeposit": {
    "precision": 1.0,
    "recall": 1.0,
    "f1-score": 1.0,
    "support": 13
  },
  "pAccountSavings": {
    "precision": 1.0,
    "recall": 1.0,
    "f1-score": 1.0,
    "support": 15
  },
  "pAccountIgnitionFreeDebitCard": {
    "precision": 1.0,
    "recall": 1.0,
    "f1-score": 1.0,
    "support": 13
  },
  "pAccountSavingsCurrency": {
    "precision": 1.0,
    "recall": 1.0,
    "f1-score": 1.0,
    "support": 15
  },
  "pAccountFixedDepositInterestPayoutFrequency": {
    "precision": 1.0,
    "recall": 1.0,
    "f1-score": 1.0,
    "support": 15
  },
  "pAccountSavingsInterestRate": {
    "precision": 1.0,
    "recall": 1.0,
    "f1-score": 1.0,
    "support": 15
  },
  "pAccountBudget": {
    "precision": 1.0,
    "recall": 1.0,
    "f1-score": 1.0,
    "support": 15
  },
  "pAccountPrestigeCurrentCurrency": {
    "precision": 1.0,
    "recall": 1.0,
    "f1-score": 1.0,
    "support": 15
  },
  "pAccountPrestigeCurrentODFacility": {
    "precision": 1.0,
    "recall": 1.0,
    "f1-score": 1.0,
    "support": 13
  },
  "pAccountPrestigeCurrent": {
    "precision": 1.0,
    "recall": 1.0,
    "f1-score": 1.0,
    "support": 15
  },
  "pAccountPrestigeCurrentMinimumInitialDeposit": {
    "precision": 1.0,
    "recall": 1.0,
    "f1-score": 1.0,
    "support": 13
  },
  "pAccountPrestigeCurrentHowApply": {
    "precision": 1.0,
    "recall": 1.0,
    "f1-score": 1.0,
    "support": 14
  },
  "micro avg": {
    "precision": 0.9992181391712275,
    "recall": 0.9992181391712275,
    "f1-score": 0.9992181391712275,
    "support": 1279
  },
  "macro avg": {
    "precision": 0.9993961352657005,
    "recall": 0.9993961352657005,
    "f1-score": 0.9993788819875777,
    "support": 1279
  },
  "weighted avg": {
    "precision": 0.9992615758839372,
    "recall": 0.9992181391712275,
    "f1-score": 0.9992181391712275,
    "support": 1279
  }
}